jyg/__init__.py
jyg/__main__.py
jyg/_version.py
jyg/constants.py
jyg/handlers.py
jyg/jygapp.py
jyg/manager.py
jyg/py.typed
jyg/serverextension.py
jyg/utils.py
jyg/_d/etc/jupyter/jupyter_notebook_config.d/jyg.json
jyg/_d/etc/jupyter/jupyter_server_config.d/jyg.json
jyg/_d/share/jupyter/labextensions/@deathbeds/jyg/package.json
jyg/_d/share/jupyter/labextensions/@deathbeds/jyg/schemas/@deathbeds/jyg/boards.json
jyg/_d/share/jupyter/labextensions/@deathbeds/jyg/schemas/@deathbeds/jyg/package.json.orig
jyg/_d/share/jupyter/labextensions/@deathbeds/jyg/schemas/@deathbeds/jyg/window-proxy.json
jyg/_d/share/jupyter/labextensions/@deathbeds/jyg/static/101.b14b8c98dade650fe22f.js
jyg/_d/share/jupyter/labextensions/@deathbeds/jyg/static/101.b14b8c98dade650fe22f.js.map
jyg/_d/share/jupyter/labextensions/@deathbeds/jyg/static/187.d59b889a9ab5b2ddcf6b.js
jyg/_d/share/jupyter/labextensions/@deathbeds/jyg/static/187.d59b889a9ab5b2ddcf6b.js.map
jyg/_d/share/jupyter/labextensions/@deathbeds/jyg/static/1fa8427b58a5e735d8d2.html
jyg/_d/share/jupyter/labextensions/@deathbeds/jyg/static/374f9193de3c5dc9a1366c1197cbe1ea3a816f79e538bcde6ce79efbb56bb27d.html
jyg/_d/share/jupyter/labextensions/@deathbeds/jyg/static/440.a38f830807f3c7273c1a.js
jyg/_d/share/jupyter/labextensions/@deathbeds/jyg/static/440.a38f830807f3c7273c1a.js.LICENSE.txt
jyg/_d/share/jupyter/labextensions/@deathbeds/jyg/static/440.a38f830807f3c7273c1a.js.map
jyg/_d/share/jupyter/labextensions/@deathbeds/jyg/static/523.0d8ff1e5ff6f303b1300.js
jyg/_d/share/jupyter/labextensions/@deathbeds/jyg/static/523.0d8ff1e5ff6f303b1300.js.map
jyg/_d/share/jupyter/labextensions/@deathbeds/jyg/static/856.9cfafe8a6d087f566ff3.js
jyg/_d/share/jupyter/labextensions/@deathbeds/jyg/static/856.9cfafe8a6d087f566ff3.js.map
jyg/_d/share/jupyter/labextensions/@deathbeds/jyg/static/remoteEntry.34b6e7347e7f66257b7f.js
jyg/_d/share/jupyter/labextensions/@deathbeds/jyg/static/remoteEntry.34b6e7347e7f66257b7f.js.map
jyg-0.1.2.dist-info/entry_points.txt
jyg-0.1.2.dist-info/LICENSE
jyg-0.1.2.dist-info/WHEEL
jyg-0.1.2.dist-info/METADATA
jyg-0.1.2.dist-info/RECORD
