Metadata-Version: 2.1
Name: jyg
Version: 0.1.2
Summary: Main entrypoint for jyg.
Author-email: jyg contributors <deathbeds@googlegroups.com>
Requires-Python: >=3.8
Classifier: Framework :: Jupyter :: JupyterLab :: 3
Classifier: Framework :: Jupyter :: JupyterLab :: Extensions :: Prebuilt
Classifier: Framework :: Jupyter :: JupyterLab :: Extensions
Classifier: Framework :: Jupyter :: JupyterLab
Classifier: Framework :: Jupyter
Classifier: License :: OSI Approved :: BSD License
Classifier: Programming Language :: Python :: 3 :: Only
Classifier: Programming Language :: Python :: 3
Requires-Dist: jinja2
Requires-Dist: jsonschema
Requires-Dist: jupyter-core>=4.7.1
Requires-Dist: jupyterlab<4,>=3.1 ; extra == "lab"
Requires-Dist: jupyter-server<2 ; extra == "notebook"
Requires-Dist: notebook<7 ; extra == "notebook"
Requires-Dist: jupyter-server ; extra == "serverextension"
Project-URL: Bug Tracker, https://github.com/deathbeds/jyg/issues
Project-URL: Changelog, https://github.com/deathbeds/jyg/blob/main/CHANGELOG.md
Project-URL: Documentation, https://jyg.rtfd.io
Project-URL: Source, https://github.com/deathbeds/jyg
Provides-Extra: lab
Provides-Extra: notebook
Provides-Extra: serverextension
